auto_remote_sync-1.2.dist-info/licenses/LICENSE
autorsync/__init__.py
autorsync/__main__.py
auto_remote_sync-1.2.dist-info/METADATA
auto_remote_sync-1.2.dist-info/WHEEL
auto_remote_sync-1.2.dist-info/entry_points.txt
auto_remote_sync-1.2.dist-info/top_level.txt
auto_remote_sync-1.2.dist-info/RECORD
