Metadata-Version: 2.4
Name: auto_remote_sync
Version: 1.2
Summary: Automate execution of various rsync commands based on profiles defined on a YAML configuration file
Author-email: Avi Alkalay <avi@unix.sh>
Project-URL: Homepage, https://github.com/avibrazil/autorsync
Project-URL: Source, https://github.com/avibrazil/autorsync
Project-URL: Issues, https://github.com/avibrazil/autorsync/issues/new/choose
Project-URL: Pypi, https://pypi.org/project/auto-remote-sync
Classifier: Programming Language :: Python :: 3
Classifier: Operating System :: OS Independent
Classifier: Development Status :: 5 - Production/Stable
Classifier: Environment :: MacOS X
Classifier: Environment :: Win32 (MS Windows)
Classifier: Environment :: Console
Classifier: Intended Audience :: System Administrators
Classifier: Intended Audience :: End Users/Desktop
Classifier: License :: OSI Approved :: GNU Library or Lesser General Public License (LGPL)
Classifier: Operating System :: MacOS
Classifier: Operating System :: Microsoft :: Windows
Classifier: Operating System :: POSIX
Classifier: Operating System :: Unix
Classifier: Topic :: System :: Archiving :: Backup
Classifier: Topic :: System :: Recovery Tools
Requires-Python: >=3.7
License-File: LICENSE
Requires-Dist: jinja2
Requires-Dist: pyyaml
Dynamic: license-file
